elektra/__init__.py
elektra/elektra.py
elektra/exceptions.py
elektra/utils.py
tests/__init__.py
tests/test.py
tests/test_caiso.py
tests/test_dst.py
elektra-0.0.31.dist-info/LICENSE
elektra-0.0.31.dist-info/METADATA
elektra-0.0.31.dist-info/WHEEL
elektra-0.0.31.dist-info/top_level.txt
elektra-0.0.31.dist-info/RECORD
