Metadata-Version: 2.1
Name: elektra
Version: 0.0.31
Summary: Power block price creation and conversion
Home-page: https://github.com/wearemolecule/elektra
Author: Molecule
Author-email: dev@molecule.io
Classifier: Programming Language :: Python :: 3
Classifier: License :: OSI Approved :: MIT License
Classifier: Operating System :: OS Independent
Requires-Python: >=3.7
License-File: LICENSE
Requires-Dist: pandas
Requires-Dist: numpy
